{
  "namespaces": [
    "public"
  ],
  "name": "public",
  "tables": [
    {
      "columns": {
        "id": {
          "name": "id",
          "type": "text",
          "unsigned": false,
          "autoincrement": false,
          "primary": true,
          "nullable": false,
          "unique": false,
          "length": null,
          "precision": null,
          "scale": null,
          "default": null,
          "comment": null,
          "enumItems": [],
          "mappedType": "text"
        },
        "name": {
          "name": "name",
          "type": "text",
          "unsigned": false,
          "autoincrement": false,
          "primary": false,
          "nullable": false,
          "unique": false,
          "length": null,
          "precision": null,
          "scale": null,
          "default": null,
          "comment": null,
          "enumItems": [],
          "mappedType": "text"
        },
        "merchant_id": {
          "name": "merchant_id",
          "type": "text",
          "unsigned": false,
          "autoincrement": false,
          "primary": false,
          "nullable": false,
          "unique": false,
          "length": null,
          "precision": null,
          "scale": null,
          "default": null,
          "comment": null,
          "enumItems": [],
          "mappedType": "text"
        },
        "client_id": {
          "name": "client_id",
          "type": "text",
          "unsigned": false,
          "autoincrement": false,
          "primary": false,
          "nullable": false,
          "unique": false,
          "length": null,
          "precision": null,
          "scale": null,
          "default": null,
          "comment": null,
          "enumItems": [],
          "mappedType": "text"
        },
        "client_secret": {
          "name": "client_secret",
          "type": "jsonb",
          "unsigned": false,
          "autoincrement": false,
          "primary": false,
          "nullable": false,
          "unique": false,
          "length": null,
          "precision": null,
          "scale": null,
          "default": null,
          "comment": null,
          "enumItems": [],
          "mappedType": "json"
        },
        "redirect_uri": {
          "name": "redirect_uri",
          "type": "text",
          "unsigned": false,
          "autoincrement": false,
          "primary": false,
          "nullable": false,
          "unique": false,
          "length": null,
          "precision": null,
          "scale": null,
          "default": null,
          "comment": null,
          "enumItems": [],
          "mappedType": "text"
        },
        "scope": {
          "name": "scope",
          "type": "text",
          "unsigned": false,
          "autoincrement": false,
          "primary": false,
          "nullable": true,
          "unique": false,
          "length": null,
          "precision": null,
          "scale": null,
          "default": null,
          "comment": null,
          "enumItems": [],
          "mappedType": "text"
        },
        "access_token": {
          "name": "access_token",
          "type": "text",
          "unsigned": false,
          "autoincrement": false,
          "primary": false,
          "nullable": true,
          "unique": false,
          "length": null,
          "precision": null,
          "scale": null,
          "default": null,
          "comment": null,
          "enumItems": [],
          "mappedType": "text"
        },
        "refresh_token": {
          "name": "refresh_token",
          "type": "jsonb",
          "unsigned": false,
          "autoincrement": false,
          "primary": false,
          "nullable": true,
          "unique": false,
          "length": null,
          "precision": null,
          "scale": null,
          "default": null,
          "comment": null,
          "enumItems": [],
          "mappedType": "json"
        },
        "token_expires_at": {
          "name": "token_expires_at",
          "type": "timestamptz",
          "unsigned": false,
          "autoincrement": false,
          "primary": false,
          "nullable": true,
          "unique": false,
          "length": 6,
          "precision": null,
          "scale": null,
          "default": null,
          "comment": null,
          "enumItems": [],
          "mappedType": "datetime"
        },
        "account_email": {
          "name": "account_email",
          "type": "text",
          "unsigned": false,
          "autoincrement": false,
          "primary": false,
          "nullable": true,
          "unique": false,
          "length": null,
          "precision": null,
          "scale": null,
          "default": null,
          "comment": null,
          "enumItems": [],
          "mappedType": "text"
        },
        "is_active": {
          "name": "is_active",
          "type": "boolean",
          "unsigned": false,
          "autoincrement": false,
          "primary": false,
          "nullable": false,
          "unique": false,
          "length": null,
          "precision": null,
          "scale": null,
          "default": "false",
          "comment": null,
          "enumItems": [],
          "mappedType": "boolean"
        },
        "api_config": {
          "name": "api_config",
          "type": "jsonb",
          "unsigned": false,
          "autoincrement": false,
          "primary": false,
          "nullable": true,
          "unique": false,
          "length": null,
          "precision": null,
          "scale": null,
          "default": null,
          "comment": null,
          "enumItems": [],
          "mappedType": "json"
        },
        "created_at": {
          "name": "created_at",
          "type": "timestamptz",
          "unsigned": false,
          "autoincrement": false,
          "primary": false,
          "nullable": false,
          "unique": false,
          "length": 6,
          "precision": null,
          "scale": null,
          "default": "now()",
          "comment": null,
          "enumItems": [],
          "mappedType": "datetime"
        },
        "updated_at": {
          "name": "updated_at",
          "type": "timestamptz",
          "unsigned": false,
          "autoincrement": false,
          "primary": false,
          "nullable": false,
          "unique": false,
          "length": 6,
          "precision": null,
          "scale": null,
          "default": "now()",
          "comment": null,
          "enumItems": [],
          "mappedType": "datetime"
        },
        "deleted_at": {
          "name": "deleted_at",
          "type": "timestamptz",
          "unsigned": false,
          "autoincrement": false,
          "primary": false,
          "nullable": true,
          "unique": false,
          "length": 6,
          "precision": null,
          "scale": null,
          "default": null,
          "comment": null,
          "enumItems": [],
          "mappedType": "datetime"
        }
      },
      "name": "google_merchant_account",
      "schema": "public",
      "indexes": [
        {
          "keyName": "IDX_google_merchant_account_deleted_at",
          "columnNames": [],
          "composite": false,
          "constraint": false,
          "primary": false,
          "unique": false,
          "expression": "CREATE INDEX IF NOT EXISTS \"IDX_google_merchant_account_deleted_at\" ON \"google_merchant_account\" (\"deleted_at\") WHERE deleted_at IS NULL"
        },
        {
          "keyName": "google_merchant_account_pkey",
          "columnNames": [
            "id"
          ],
          "composite": false,
          "constraint": true,
          "primary": true,
          "unique": true
        }
      ],
      "checks": [],
      "foreignKeys": {},
      "nativeEnums": {}
    },
    {
      "columns": {
        "id": {
          "name": "id",
          "type": "text",
          "unsigned": false,
          "autoincrement": false,
          "primary": true,
          "nullable": false,
          "unique": false,
          "length": null,
          "precision": null,
          "scale": null,
          "default": null,
          "comment": null,
          "enumItems": [],
          "mappedType": "text"
        },
        "transaction_id": {
          "name": "transaction_id",
          "type": "text",
          "unsigned": false,
          "autoincrement": false,
          "primary": false,
          "nullable": true,
          "unique": false,
          "length": null,
          "precision": null,
          "scale": null,
          "default": null,
          "comment": null,
          "enumItems": [],
          "mappedType": "text"
        },
        "account_id": {
          "name": "account_id",
          "type": "text",
          "unsigned": false,
          "autoincrement": false,
          "primary": false,
          "nullable": false,
          "unique": false,
          "length": null,
          "precision": null,
          "scale": null,
          "default": null,
          "comment": null,
          "enumItems": [],
          "mappedType": "text"
        },
        "status": {
          "name": "status",
          "type": "text",
          "unsigned": false,
          "autoincrement": false,
          "primary": false,
          "nullable": false,
          "unique": false,
          "length": null,
          "precision": null,
          "scale": null,
          "default": "'pending'",
          "comment": null,
          "enumItems": [
            "pending",
            "processing",
            "completed",
            "failed"
          ],
          "mappedType": "enum"
        },
        "total_products": {
          "name": "total_products",
          "type": "integer",
          "unsigned": false,
          "autoincrement": false,
          "primary": false,
          "nullable": false,
          "unique": false,
          "length": null,
          "precision": null,
          "scale": null,
          "default": "0",
          "comment": null,
          "enumItems": [],
          "mappedType": "integer"
        },
        "synced_count": {
          "name": "synced_count",
          "type": "integer",
          "unsigned": false,
          "autoincrement": false,
          "primary": false,
          "nullable": false,
          "unique": false,
          "length": null,
          "precision": null,
          "scale": null,
          "default": "0",
          "comment": null,
          "enumItems": [],
          "mappedType": "integer"
        },
        "failed_count": {
          "name": "failed_count",
          "type": "integer",
          "unsigned": false,
          "autoincrement": false,
          "primary": false,
          "nullable": false,
          "unique": false,
          "length": null,
          "precision": null,
          "scale": null,
          "default": "0",
          "comment": null,
          "enumItems": [],
          "mappedType": "integer"
        },
        "error_log": {
          "name": "error_log",
          "type": "jsonb",
          "unsigned": false,
          "autoincrement": false,
          "primary": false,
          "nullable": true,
          "unique": false,
          "length": null,
          "precision": null,
          "scale": null,
          "default": null,
          "comment": null,
          "enumItems": [],
          "mappedType": "json"
        },
        "started_at": {
          "name": "started_at",
          "type": "timestamptz",
          "unsigned": false,
          "autoincrement": false,
          "primary": false,
          "nullable": true,
          "unique": false,
          "length": 6,
          "precision": null,
          "scale": null,
          "default": null,
          "comment": null,
          "enumItems": [],
          "mappedType": "datetime"
        },
        "completed_at": {
          "name": "completed_at",
          "type": "timestamptz",
          "unsigned": false,
          "autoincrement": false,
          "primary": false,
          "nullable": true,
          "unique": false,
          "length": 6,
          "precision": null,
          "scale": null,
          "default": null,
          "comment": null,
          "enumItems": [],
          "mappedType": "datetime"
        },
        "created_at": {
          "name": "created_at",
          "type": "timestamptz",
          "unsigned": false,
          "autoincrement": false,
          "primary": false,
          "nullable": false,
          "unique": false,
          "length": 6,
          "precision": null,
          "scale": null,
          "default": "now()",
          "comment": null,
          "enumItems": [],
          "mappedType": "datetime"
        },
        "updated_at": {
          "name": "updated_at",
          "type": "timestamptz",
          "unsigned": false,
          "autoincrement": false,
          "primary": false,
          "nullable": false,
          "unique": false,
          "length": 6,
          "precision": null,
          "scale": null,
          "default": "now()",
          "comment": null,
          "enumItems": [],
          "mappedType": "datetime"
        },
        "deleted_at": {
          "name": "deleted_at",
          "type": "timestamptz",
          "unsigned": false,
          "autoincrement": false,
          "primary": false,
          "nullable": true,
          "unique": false,
          "length": 6,
          "precision": null,
          "scale": null,
          "default": null,
          "comment": null,
          "enumItems": [],
          "mappedType": "datetime"
        }
      },
      "name": "google_merchant_sync_job",
      "schema": "public",
      "indexes": [
        {
          "keyName": "IDX_google_merchant_sync_job_deleted_at",
          "columnNames": [],
          "composite": false,
          "constraint": false,
          "primary": false,
          "unique": false,
          "expression": "CREATE INDEX IF NOT EXISTS \"IDX_google_merchant_sync_job_deleted_at\" ON \"google_merchant_sync_job\" (\"deleted_at\") WHERE deleted_at IS NULL"
        },
        {
          "keyName": "google_merchant_sync_job_pkey",
          "columnNames": [
            "id"
          ],
          "composite": false,
          "constraint": true,
          "primary": true,
          "unique": true
        }
      ],
      "checks": [],
      "foreignKeys": {},
      "nativeEnums": {}
    }
  ],
  "nativeEnums": {}
}
